loggedfs/__init__.py
loggedfs/_core/__init__.py
loggedfs/_core/cli.py
loggedfs/_core/defaults.py
loggedfs/_core/filter.py
loggedfs/_core/fs.py
loggedfs/_core/ipc.py
loggedfs/_core/log.py
loggedfs/_core/notify.py
loggedfs/_core/out.py
loggedfs/_core/timing.py
loggedfs-0.0.6.dist-info/LICENSE
loggedfs-0.0.6.dist-info/METADATA
loggedfs-0.0.6.dist-info/WHEEL
loggedfs-0.0.6.dist-info/entry_points.txt
loggedfs-0.0.6.dist-info/top_level.txt
loggedfs-0.0.6.dist-info/RECORD
