Metadata-Version: 2.1
Name: loggedfs
Version: 0.0.6
Summary: Filesystem monitoring with Fuse and Python
Home-page: https://github.com/pleiszenburg/loggedfs-python
Author: Sebastian M. Ernst
Author-email: ernst@pleiszenburg.de
License: Apache License 2.0
Download-URL: https://github.com/pleiszenburg/loggedfs-python/archive/v0.0.6.tar.gz
Keywords: filesystem,fuse,logging,monitoring
Platform: UNKNOWN
Classifier: Development Status :: 4 - Beta
Classifier: Environment :: Console
Classifier: Intended Audience :: Developers
Classifier: Intended Audience :: Information Technology
Classifier: Intended Audience :: Science/Research
Classifier: Intended Audience :: System Administrators
Classifier: License :: OSI Approved :: Apache Software License
Classifier: Operating System :: POSIX :: Linux
Classifier: Operating System :: MacOS
Classifier: Programming Language :: Python :: 3
Classifier: Programming Language :: Python :: 3.5
Classifier: Programming Language :: Python :: 3.6
Classifier: Programming Language :: Python :: 3.7
Classifier: Programming Language :: Python :: 3.8
Classifier: Programming Language :: Python :: 3 :: Only
Classifier: Programming Language :: Python :: Implementation :: CPython
Classifier: Topic :: Scientific/Engineering
Classifier: Topic :: Software Development :: Libraries
Classifier: Topic :: Software Development :: Testing
Classifier: Topic :: System :: Archiving
Classifier: Topic :: System :: Filesystems
Classifier: Topic :: System :: Logging
Classifier: Topic :: System :: Monitoring
Classifier: Topic :: System :: Systems Administration
Classifier: Topic :: Utilities
Requires-Python: >=3.5
Requires-Dist: click (>=7.0)
Requires-Dist: refuse (==0.0.4)
Requires-Dist: xmltodict
Provides-Extra: dev
Requires-Dist: coverage ; extra == 'dev'
Requires-Dist: psutil ; extra == 'dev'
Requires-Dist: pytest ; extra == 'dev'
Requires-Dist: python-language-server[all] ; extra == 'dev'
Requires-Dist: PyYAML ; extra == 'dev'
Requires-Dist: setuptools ; extra == 'dev'
Requires-Dist: Sphinx ; extra == 'dev'
Requires-Dist: sphinx-rtd-theme ; extra == 'dev'
Requires-Dist: tap.py ; extra == 'dev'
Requires-Dist: twine ; extra == 'dev'
Requires-Dist: wheel ; extra == 'dev'
